<annotation>
	<folder>images_annotated</folder>
	<filename>sr_0_295.png</filename>
	<path>D:\images_annotated\sr_0_295.png</path>
	<source>
		<database>Unknown</database>
	</source>
	<size>
		<width>1366</width>
		<height>768</height>
		<depth>3</depth>
	</size>
	<segmented>0</segmented>
	<object>
		<name>noresultsfound</name>
		<pose>Unspecified</pose>
		<truncated>0</truncated>
		<difficult>0</difficult>
		<bndbox>
			<xmin>360</xmin>
			<ymin>79</ymin>
			<xmax>682</xmax>
			<ymax>163</ymax>
		</bndbox>
	</object>
	<object>
		<name>searchtextbox</name>
		<pose>Unspecified</pose>
		<truncated>1</truncated>
		<difficult>0</difficult>
		<bndbox>
			<xmin>922</xmin>
			<ymin>1</ymin>
			<xmax>1366</xmax>
			<ymax>70</ymax>
		</bndbox>
	</object>
</annotation>
