<annotation>
	<folder>images_annotated</folder>
	<filename>sr_0_1629.png</filename>
	<path>D:\images_annotated\sr_0_1629.png</path>
	<source>
		<database>Unknown</database>
	</source>
	<size>
		<width>1366</width>
		<height>768</height>
		<depth>3</depth>
	</size>
	<segmented>0</segmented>
	<object>
		<name>myaccountbutton</name>
		<pose>Unspecified</pose>
		<truncated>0</truncated>
		<difficult>0</difficult>
		<bndbox>
			<xmin>496</xmin>
			<ymin>67</ymin>
			<xmax>635</xmax>
			<ymax>116</ymax>
		</bndbox>
	</object>
	<object>
		<name>noresultsfound</name>
		<pose>Unspecified</pose>
		<truncated>1</truncated>
		<difficult>0</difficult>
		<bndbox>
			<xmin>1</xmin>
			<ymin>261</ymin>
			<xmax>98</xmax>
			<ymax>300</ymax>
		</bndbox>
	</object>
	<object>
		<name>searchicon</name>
		<pose>Unspecified</pose>
		<truncated>0</truncated>
		<difficult>0</difficult>
		<bndbox>
			<xmin>972</xmin>
			<ymin>49</ymin>
			<xmax>1016</xmax>
			<ymax>89</ymax>
		</bndbox>
	</object>
</annotation>
